probely/__init__.py
probely/__main__.py
probely/constants.py
probely/exceptions.py
probely/settings.py
probely/version.py
probely/cli/__init__.py
probely/cli/app.py
probely/cli/common.py
probely/cli/enums.py
probely/cli/renderers.py
probely/cli/commands/__init__.py
probely/cli/commands/findings/__init__.py
probely/cli/commands/findings/get.py
probely/cli/commands/findings/schemas.py
probely/cli/commands/scan_profiles/__init__.py
probely/cli/commands/scan_profiles/get.py
probely/cli/commands/scan_profiles/schemas.py
probely/cli/commands/scans/__init__.py
probely/cli/commands/scans/cancel.py
probely/cli/commands/scans/get.py
probely/cli/commands/scans/pause.py
probely/cli/commands/scans/resume.py
probely/cli/commands/scans/schemas.py
probely/cli/commands/target_extra_hosts/__init__.py
probely/cli/commands/target_extra_hosts/add.py
probely/cli/commands/target_extra_hosts/delete.py
probely/cli/commands/target_extra_hosts/get.py
probely/cli/commands/target_extra_hosts/schemas.py
probely/cli/commands/target_extra_hosts/update.py
probely/cli/commands/target_labels/__init__.py
probely/cli/commands/target_labels/get.py
probely/cli/commands/target_sequences/__init__.py
probely/cli/commands/target_sequences/delete.py
probely/cli/commands/target_sequences/get.py
probely/cli/commands/target_sequences/schemas.py
probely/cli/commands/target_sequences/update.py
probely/cli/commands/targets/__init__.py
probely/cli/commands/targets/add.py
probely/cli/commands/targets/add_sequence.py
probely/cli/commands/targets/delete.py
probely/cli/commands/targets/get.py
probely/cli/commands/targets/schemas.py
probely/cli/commands/targets/start_scan.py
probely/cli/commands/targets/update.py
probely/cli/parsers/__init__.py
probely/cli/parsers/base_parser.py
probely/cli/parsers/common.py
probely/cli/parsers/extra_hosts_parser.py
probely/cli/parsers/findings_parsers.py
probely/cli/parsers/help_texts.py
probely/cli/parsers/scan_profiles_parsers.py
probely/cli/parsers/scans_parsers.py
probely-0.1.0.dist-info/METADATA
probely-0.1.0.dist-info/WHEEL
probely-0.1.0.dist-info/entry_points.txt
probely-0.1.0.dist-info/licenses/LICENSE
probely-0.1.0.dist-info/RECORD
