Metadata-Version: 2.4
Name: probely
Version: 0.1.0
Summary: CLI and SDK wrappers for Probely's API
Project-URL: Homepage, https://probely.com
Project-URL: Documentation, https://developers.probely.com
Project-URL: Repository, https://github.com/probely/probely-python.git
Project-URL: Bug Tracker, https://github.com/probely/probely-python/issues
Author-email: Probely <hello@probely.com>
Maintainer-email: João Silva <joao.silva@probely.com>, Vladimir Kontic <vladimir@probely.com>, Temidire Adams <temidire@probely.com>
License: BSD 3-Clause License
License-File: LICENSE
Keywords: api,cli,client,probely,sdk,wrapper
Classifier: Development Status :: 3 - Alpha
Classifier: Environment :: Console
Classifier: Intended Audience :: Developers
Classifier: Intended Audience :: Other Audience
Classifier: Intended Audience :: System Administrators
Classifier: License :: OSI Approved :: BSD License
Classifier: Natural Language :: English
Classifier: Operating System :: OS Independent
Classifier: Programming Language :: Python :: 3
Classifier: Programming Language :: Python :: 3.8
Classifier: Programming Language :: Python :: 3.9
Classifier: Programming Language :: Python :: 3.10
Classifier: Programming Language :: Python :: 3.11
Classifier: Programming Language :: Python :: 3.12
Classifier: Programming Language :: Python :: 3.13
Classifier: Topic :: Software Development
Classifier: Topic :: Software Development :: Libraries
Requires-Python: >=3.8
Requires-Dist: environs
Requires-Dist: marshmallow
Requires-Dist: mergedeep
Requires-Dist: pydantic[email]
Requires-Dist: python-dateutil
Requires-Dist: pyyaml
Requires-Dist: requests
Requires-Dist: rich
Requires-Dist: rich-argparse
Requires-Dist: toml
Provides-Extra: dev
Requires-Dist: datamodel-code-generator; extra == 'dev'
Requires-Dist: hatch; extra == 'dev'
Requires-Dist: pre-commit; extra == 'dev'
Requires-Dist: pytest; extra == 'dev'
Requires-Dist: ruff==0.8.6; extra == 'dev'
Requires-Dist: tox; extra == 'dev'
Provides-Extra: docs
Requires-Dist: sphinx; extra == 'docs'
Requires-Dist: sphinx-argparse-cli; extra == 'docs'
Requires-Dist: sphinx-markdown-builder; extra == 'docs'
